{
  "company_name": "G&M Pressure Washing",
  "industry_type": "electrical contracting",
  "services_supported": [
    "service calls",
    "small jobs",
    "odd jobs",
    "renovations",
    "troubleshooting",
    "new custom homes",
    "tenant improvements",
    "EV charger installations",
    "hot tub hookups",
    "panel changes",
    "outlet replacements",
    "aluminum wiring remediation",
    "LED upgrades",
    "GFCI protection installation",
    "hot tub plumbing and gas line connections"
  ],
  "business_hours": {
    "days": [
      "Monday",
      "Tuesday",
      "Wednesday",
      "Thursday",
      "Friday"
    ],
    "start": "08:30",
    "end": "17:00",
    "timezone": null
  },
  "office_address": null,
  "emergency_definition": [
    "existing builders",
    "property manager (G&M Pressure Washing)"
  ],
  "emergency_routing_rules": {
    "contacts": [],
    "fallback": null
  },
  "non_emergency_routing_rules": {
    "action": "return call next business day",
    "fallback": null
  },
  "call_transfer_rules": {
    "timeout_seconds": null,
    "retries": null,
    "on_fail": null
  },
  "integration_constraints": "Vendor will use the client company's website to train the AI agent.",
  "after_hours_flow_summary": "Policy is to return the call the next business day.",
  "office_hours_flow_summary": "During business hours Clara answers calls, routes them to the appropriate team member based on the service requested, supports multiple languages, assigns calls, and provides a dashboard for call tracking and analytics.",
  "questions_or_unknowns": [
    "What are the specific business days (e.g., Monday‑Friday)?",
    "What is the end time for business hours?",
    "What is the timezone of the business?",
    "What is the office or billing address?",
    "What is the primary business phone number in E.164 format?",
    "Who are the emergency contact persons with phone numbers and priority levels?",
    "Are there any specific non‑emergency routing actions (e.g., voicemail, queue)?"
  ],
  "notes": "Follow-up meeting scheduled for Friday at 2:00 PM to review the setup.",
  "account_id": "demo_001"
}
